gunicorn_torify/__init__.py
gunicorn_torify/_version.py
gunicorn_torify/api.py
gunicorn_torify/config.py
gunicorn_torify-19.12.2710.dist-info/LICENSE
gunicorn_torify-19.12.2710.dist-info/METADATA
gunicorn_torify-19.12.2710.dist-info/WHEEL
gunicorn_torify-19.12.2710.dist-info/top_level.txt
gunicorn_torify-19.12.2710.dist-info/RECORD
