Metadata-Version: 2.1
Name: gunicorn-torify
Version: 19.12.2710
Summary: Turn any Gunicorn application into a Tor Onion Service
Home-page: https://gitlab.com/afiorillo/gunicorn-torify/
Author: Andrew Fiorillo
Author-email: andrewmfiorillo@gmail.com
License: UNKNOWN
Platform: UNKNOWN
Classifier: Programming Language :: Python :: 3
Classifier: License :: OSI Approved :: BSD License
Classifier: Operating System :: POSIX :: Linux
Requires-Python: >=3.5
